djangoldp_stripe/__init__.py
djangoldp_stripe/apps.py
djangoldp_stripe/djangoldp_settings.py
djangoldp_stripe/djangoldp_urls.py
djangoldp_stripe/middleware.py
djangoldp_stripe/permissions.py
djangoldp_stripe/views.py
djangoldp_stripe/static/style.css
djangoldp_stripe/static/img/validate.png
djangoldp_stripe/templates/base.html
djangoldp_stripe/templates/cancel.html
djangoldp_stripe/templates/checkout.html
djangoldp_stripe/templates/success.html
djangoldp_stripe-1.0.0.dist-info/METADATA
djangoldp_stripe-1.0.0.dist-info/WHEEL
djangoldp_stripe-1.0.0.dist-info/top_level.txt
djangoldp_stripe-1.0.0.dist-info/RECORD
