Metadata-Version: 2.4
Name: djangoldp_stripe
Version: 1.0.0
Summary: djangoldp package for working with Stripe payments
Home-page: https://git.startinblox.com/djangoldp-packages/djangoldp-stripe
Author: StartinBlox
Author-email: calum@startinblox.com
Requires-Dist: djangoldp~=5.0.0
Requires-Dist: dj-stripe~=2.5.1
Requires-Dist: stripe==2.60.0
Provides-Extra: dev
Requires-Dist: factory_boy>=3.2.1; extra == "dev"
